stepfunction_validator/__init__.py
stepfunction_validator/__main__.py
stepfunction_validator/cli.py
stepfunction_validator/stepfunction_validator.py
stepfunction_validator/stepfunctions_schema.json
stepfunction_validator-0.0.5.dist-info/METADATA
stepfunction_validator-0.0.5.dist-info/WHEEL
stepfunction_validator-0.0.5.dist-info/entry_points.txt
stepfunction_validator-0.0.5.dist-info/top_level.txt
stepfunction_validator-0.0.5.dist-info/RECORD
